project.v
/* Line following Maze Solver using LSRB Algorithm
L-left, S-straight, R-right, B-back(turn around)
Robot follows the above given priority if a junction is detected*/
module linefollower(LSRB,s,straight,stop,left,right,turn_around,left_motor_forward,left_motor_backward,left_motor_right,left_motor_left,right_motor_forward,right_motor_backward,right_motor_right,right_motor_left);
input [0:3] LSRB; // Next move input
output [0:4] s; // 5-Sensors
output straight; // Move forward
output stop; // Stop
output left; // Turn left
output right; // Turn right
output turn_around; // Turn around
output reg left_motor_forward,left_motor_backward,left_motor_right,left_motor_left; // Specifies the direction of left motor
output reg right_motor_forward,right_motor_backward,right_motor_right,right_motor_left; // Specifies the direction of right motor

//data flow modelling
assign s[0]=(~LSRB[0]&LSRB[1])|(~LSRB[0]&~LSRB[2]&~LSRB[3]);
assign s[1]=(~LSRB[0]&~LSRB[1]&LSRB[2])|(~LSRB[0]&~LSRB[1]&~LSRB[3]);
assign s[3]=(~LSRB[0]&~LSRB[1]&~LSRB[2]&~LSRB[3]);
assign s[4]=LSRB[0]|(~LSRB[1]&~LSRB[2]&~LSRB[3]);
assign s[2]=s[0]|s[1]|s[3]|s[4]|LSRB[3];

assign straight = s[0]&s[2]&~s[3]&~s[4];
assign stop = s[0]&s[1]&s[2]&s[3]&s[4];
assign left = s[2]&~s[3]&s[4];
assign right = ~s[0]&s[1]&s[2]&~s[3]&~s[4];
assign turn_around = s[2]&~s[0]&~s[1]&~s[3]&~s[4];

//behavioural modelling
always @(*)
begin
    if(stop && !straight && !left && !right && !turn_around) begin
        left_motor_forward=1'b0; // Stop if destination is reached
        left_motor_backward=1'b0;
        left_motor_left=1'b0;
        left_motor_right=1'b0;
        right_motor_forward=1'b0;
        right_motor_backward=1'b0;
        right_motor_left=1'b0;
        right_motor_right=1'b0;
    end
    else if(straight && !stop && !left && !right && !turn_around) begin
        left_motor_forward=1'b1; // Move forward
        left_motor_backward=1'b0;
        left_motor_left=1'b0;
        left_motor_right=1'b0;
        right_motor_forward=1'b1;
        right_motor_backward=1'b0;
        right_motor_left=1'b0;
        right_motor_right=1'b0;
    end
    else if(left && !straight && !stop && !right && !turn_around) begin
        left_motor_forward=1'b0; // Turn left
        left_motor_backward=1'b0;
        left_motor_left=1'b1;
        left_motor_right=1'b0;
        right_motor_forward=1'b0;
        right_motor_backward=1'b0;
        right_motor_left=1'b1;
        right_motor_right=1'b0;
    end
    else if(right && !straight && !stop && !left && !turn_around) begin
        left_motor_forward=1'b0; // Turn right
        left_motor_backward=1'b0;
        left_motor_left=1'b0;
        left_motor_right=1'b1;
        right_motor_forward=1'b0;
        right_motor_backward=1'b0;
        right_motor_left=1'b0;
        right_motor_right=1'b1;
    end
    else if(turn_around && !straight && !stop && !left && !right) begin
        left_motor_forward=1'b1; // Turn around in clockwise direction if dead end is detected
        left_motor_backward=1'b0;
        left_motor_left=1'b0;
        left_motor_right=1'b0;
        right_motor_forward=1'b0;
        right_motor_backward=1'b1;
        right_motor_left=1'b0;
        right_motor_right=1'b0;
    end 
    else begin
        left_motor_forward=1'b0; 
        left_motor_backward=1'b0;
        left_motor_left=1'b0;
        left_motor_right=1'b0;
        right_motor_forward=1'b0;
        right_motor_backward=1'b0;
        right_motor_left=1'b0;
        right_motor_right=1'b0;
    end
end
endmodule

project_tb.v
`include "project.v"
module linefollower_tb;
reg [0:3] LSRB;
wire [0:4] s;
wire straight,stop,left,right,turn_around;
wire left_motor_forward,left_motor_backward,left_motor_right,left_motor_left;
wire right_motor_forward,right_motor_backward,right_motor_right,right_motor_left;
linefollower s1(LSRB,s,straight,stop,left,right,turn_around,left_motor_forward,left_motor_backward,left_motor_right,left_motor_left,right_motor_forward,right_motor_backward,right_motor_right,right_motor_left);

initial begin
    $dumpfile("linefollower.vcd");
    $dumpvars(0,linefollower_tb);
end

initial begin
    $display("                                                                                                          ");
    $display("                                                                                                          ");
    $display("                                           LINE FOLLOWING MAZE SOLVER                                     ");
    $display("   L       S       R       B     |           Sensor         |       Direction     |     Motor direction   ");
    $display(" LSRB[0] LSRB[1] LSRB[2] LSRB[3] | s[0] s[1] s[2] s[3] s[4] |  str stop lf rg ta  | lf lb lr ll | rf rb rr rl");
    /* str:straight   lf:left   rg:right   ta:turn around   lf:left_motor_forward   lb:left_motor_backward  ll:left_motor_left   lr:left_motor_right   rf:right_motor_forward   rb:right_motor_backward   rl:right_motor_left   rr:right_motor_right  */ 
    $display("-------------------------------------------------------------------------------------------------------------");
    $monitor("    %b      %b       %b       %b     |  %b    %b    %b    %b    %b   |  %b   %b   %b   %b   %b  |  %b  %b  %b  %b | %b  %b  %b  %b",LSRB[0],LSRB[1],LSRB[2],LSRB[3],s[0],s[1],s[2],s[3],s[4],straight,stop,left,right,turn_around,left_motor_forward,left_motor_backward,left_motor_right,left_motor_left,right_motor_forward,right_motor_backward,right_motor_right,right_motor_left);
    LSRB=4'b0000;
    repeat(15)
    #10 LSRB=LSRB+4'b0001;
    $display("                                                                                                          ");
    $display("                                                                                                          ");
    $display("                                                                                                          ");
    $display("                                  LINE FOLLOWING MAZE SOLVER WITH PREDEFINED PATH                         ");
    $display("   L       S       R       B     |           Sensor         |       Direction     |     Motor direction   ");
    $display(" LSRB[0] LSRB[1] LSRB[2] LSRB[3] | s[0] s[1] s[2] s[3] s[4] |  str stop lf rg ta  | lf lb lr ll | rf rb rr rl");
    /* str:straight   lf:left   rg:right   ta:turn around   lf:left_motor_forward   lb:left_motor_backward  ll:left_motor_left   lr:left_motor_right   rf:right_motor_forward   rb:right_motor_backward   rl:right_motor_left   rr:right_motor_right  */ 
    $display("-------------------------------------------------------------------------------------------------------------");
    $monitor("    %b      %b       %b       %b     |  %b    %b    %b    %b    %b   |  %b   %b   %b   %b   %b  |  %b  %b  %b  %b | %b  %b  %b  %b",LSRB[0],LSRB[1],LSRB[2],LSRB[3],s[0],s[1],s[2],s[3],s[4],straight,stop,left,right,turn_around,left_motor_forward,left_motor_backward,left_motor_right,left_motor_left,right_motor_forward,right_motor_backward,right_motor_right,right_motor_left);
    LSRB[0]=0;LSRB[1]=1;LSRB[2]=0;LSRB[3]=0;
    #10 LSRB[0]=1;LSRB[1]=0;LSRB[2]=0;LSRB[3]=1;
    #10 LSRB[0]=0;LSRB[1]=1;LSRB[2]=0;LSRB[3]=1;
    #10 LSRB[0]=0;LSRB[1]=0;LSRB[2]=1;LSRB[3]=1;
    #10 LSRB[0]=0;LSRB[1]=1;LSRB[2]=0;LSRB[3]=1;
    #10 LSRB[0]=1;LSRB[1]=0;LSRB[2]=0;LSRB[3]=1;
    #10 LSRB[0]=0;LSRB[1]=1;LSRB[2]=0;LSRB[3]=1;
    #10 LSRB[0]=1;LSRB[1]=0;LSRB[2]=1;LSRB[3]=1;
    #10 LSRB[0]=0;LSRB[1]=1;LSRB[2]=0;LSRB[3]=1;
    #10 LSRB[0]=0;LSRB[1]=0;LSRB[2]=0;LSRB[3]=1;
    #10 LSRB[0]=0;LSRB[1]=1;LSRB[2]=1;LSRB[3]=1;
    #10 LSRB[0]=1;LSRB[1]=0;LSRB[2]=1;LSRB[3]=1;
    #10 LSRB[0]=0;LSRB[1]=1;LSRB[2]=1;LSRB[3]=1;
    #10 LSRB[0]=1;LSRB[1]=0;LSRB[2]=1;LSRB[3]=1;
    #10 LSRB[0]=0;LSRB[1]=1;LSRB[2]=0;LSRB[3]=1;
    #10 LSRB[0]=1;LSRB[1]=1;LSRB[2]=0;LSRB[3]=1;
    #10 LSRB[0]=0;LSRB[1]=1;LSRB[2]=0;LSRB[3]=1;
    #10 LSRB[0]=0;LSRB[1]=0;LSRB[2]=1;LSRB[3]=1;
    #10 LSRB[0]=0;LSRB[1]=1;LSRB[2]=0;LSRB[3]=1;
    #10 LSRB[0]=0;LSRB[1]=0;LSRB[2]=0;LSRB[3]=0;
end

initial #500 $finish;
endmodule

Verilog/linefollower.vcd
$date
	Thu Oct 19 10:06:09 2023
$end
$version
	Icarus Verilog
$end
$timescale
	1s
$end
$scope module linefollower_tb $end
$var wire 1 ! turn_around $end
$var wire 1 " straight $end
$var wire 1 # stop $end
$var wire 5 $ s [0:4] $end
$var wire 1 % right_motor_right $end
$var wire 1 & right_motor_left $end
$var wire 1 ' right_motor_forward $end
$var wire 1 ( right_motor_backward $end
$var wire 1 ) right $end
$var wire 1 * left_motor_right $end
$var wire 1 + left_motor_left $end
$var wire 1 , left_motor_forward $end
$var wire 1 - left_motor_backward $end
$var wire 1 . left $end
$var reg 4 / LSRB [0:3] $end
$scope module s1 $end
$var wire 4 0 LSRB [0:3] $end
$var wire 1 . left $end
$var wire 1 ) right $end
$var wire 1 # stop $end
$var wire 1 " straight $end
$var wire 1 ! turn_around $end
$var wire 5 1 s [0:4] $end
$var reg 1 - left_motor_backward $end
$var reg 1 , left_motor_forward $end
$var reg 1 + left_motor_left $end
$var reg 1 * left_motor_right $end
$var reg 1 ( right_motor_backward $end
$var reg 1 ' right_motor_forward $end
$var reg 1 & right_motor_left $end
$var reg 1 % right_motor_right $end
$upscope $end
$upscope $end
$enddefinitions $end
$comment Show the parameter values. $end
$dumpall
$end
#0
$dumpvars
b11111 1
b0 0
b0 /
0.
0-
0,
0+
0*
0)
0(
0'
0&
0%
b11111 $
1#
0"
0!
$end
#10
1(
1!
0'
1,
0"
0#
b100 $
b100 1
b1 /
b1 0
#20
1%
1*
1)
0(
0,
0!
b1100 $
b1100 1
b10 /
b10 0
#30
b11 /
b11 0
#40
1'
1,
1"
0%
0*
0)
b10100 $
b10100 1
b100 /
b100 0
#50
b101 /
b101 0
#60
b110 /
b110 0
#70
b111 /
b111 0
#80
1&
1+
0"
0'
0,
1.
b101 $
b101 1
b1000 /
b1000 0
#90
b1001 /
b1001 0
#100
b1010 /
b1010 0
#110
b1011 /
b1011 0
#120
b1100 /
b1100 0
#130
b1101 /
b1101 0
#140
b1110 /
b1110 0
#150
1'
1"
0&
0(
0+
1,
0!
0.
b10100 $
b10100 1
b100 /
b100 0
#160
1&
1+
0"
0'
0,
1.
b101 $
b101 1
b1001 /
b1001 0
#170
1'
1"
0&
0(
0+
1,
0!
0.
b10100 $
b10100 1
b101 /
b101 0
#180
1%
1*
1)
0'
0,
0"
b1100 $
b1100 1
b11 /
b11 0
#190
1'
1,
0)
0%
0*
1"
b10100 $
b10100 1
b101 /
b101 0
#200
1&
1+
0"
0'
0,
1.
b101 $
b101 1
b1001 /
b1001 0
#210
1'
1"
0&
0(
0+
1,
0!
0.
b10100 $
b10100 1
b101 /
b101 0
#220
1&
1+
0"
0'
0,
1.
b101 $
b101 1
b1011 /
b1011 0
#230
1'
1"
0&
0(
0+
1,
0!
0.
b10100 $
b10100 1
b101 /
b101 0
#240
1(
1!
0'
1,
0"
b100 $
b100 1
b1 /
b1 0
#250
1'
0!
0(
1,
1"
b10100 $
b10100 1
b111 /
b111 0
#260
1&
1+
0"
0'
0,
1.
b101 $
b101 1
b1011 /
b1011 0
#270
1'
1"
0&
0(
0+
1,
0!
0.
b10100 $
b10100 1
b111 /
b111 0
#280
1&
1+
0"
0'
0,
1.
b101 $
b101 1
b1011 /
b1011 0
#290
1'
1"
0&
0(
0+
1,
0!
0.
b10100 $
b10100 1
b101 /
b101 0
#300
1&
1+
0"
0'
0,
1.
b101 $
b101 1
b1101 /
b1101 0
#310
1'
1"
0&
0(
0+
1,
0!
0.
b10100 $
b10100 1
b101 /
b101 0
#320
1%
1*
1)
0'
0,
0"
b1100 $
b1100 1
b11 /
b11 0
#330
1'
1,
0)
0%
0*
1"
b10100 $
b10100 1
b101 /
b101 0
#340
1#
0&
0'
0+
0,
0"
0.
b11111 $
b11111 1
b0 /
b0 0
